fastapi_queue_task/__init__.py
fastapi_queue_task/constants/queue_constant.py
fastapi_queue_task/loggers/format.py
fastapi_queue_task/loggers/logger.py
fastapi_queue_task/services/base_queue.py
fastapi_queue_task/services/queue_service.py
fastapi_queue_task/tasks/base.py
fastapi_queue_task/tasks/decorator.py
fastapi_queue_task/tasks/storage.py
fastapi_queue_task/type_dicts/queue_option_type.py
fastapi_queue_task/type_dicts/task_type.py
fastapi_queue_task-1.0.4.dist-info/METADATA
fastapi_queue_task-1.0.4.dist-info/WHEEL
fastapi_queue_task-1.0.4.dist-info/licenses/LICENSE
fastapi_queue_task-1.0.4.dist-info/RECORD
