Metadata-Version: 2.4
Name: fastapi_queue_task
Version: 1.0.4
Summary: FastAPI Queue
Project-URL: Homepage, https://github.com/megatron-global/fastapi-queue
Project-URL: Bug Tracker, https://github.com/megatron-global/fastapi-queue/issues
Author-email: Dzung Nguyen <dung@megatron-solutions.com>
License-File: LICENSE
Classifier: License :: OSI Approved :: MIT License
Classifier: Operating System :: OS Independent
Classifier: Programming Language :: Python :: 3
Requires-Python: >=3.10
Requires-Dist: fastapi>=0.103.1
Requires-Dist: pydash>=0.5.0
